pymsword/__init__.py
pymsword/com_utilities.py
pymsword/docx_template.py
pymsword/docxcom_template.py
pymsword/xml_template.py
pymsword-0.1.0.dist-info/licenses/LICENSE.MIT
pymsword-0.1.0.dist-info/METADATA
pymsword-0.1.0.dist-info/WHEEL
pymsword-0.1.0.dist-info/top_level.txt
pymsword-0.1.0.dist-info/RECORD
