Metadata-Version: 2.4
Name: pymsword
Version: 0.1.0
Summary: A Python library for working with Microsoft Word via COM automation
Author: KInside
License: Copyright 2025 Knowledge Inside
Classifier: License :: OSI Approved :: MIT License
Classifier: Programming Language :: Python :: 3
Requires-Python: >=3.8
License-File: LICENSE.MIT
Requires-Dist: pywin32
Requires-Dist: pillow
Dynamic: license-file
